optimal3dtracks/__init__.py
optimal3dtracks/utils_3Dtracking.py
optimal3dtracks-0.0.5.dist-info/LICENSE.md
optimal3dtracks-0.0.5.dist-info/METADATA
optimal3dtracks-0.0.5.dist-info/WHEEL
optimal3dtracks-0.0.5.dist-info/top_level.txt
optimal3dtracks-0.0.5.dist-info/RECORD
